{
    "nsf_profile": {
        "nsf_pi_id": "0000A2L4G",
        "name": "Edwin D Sookiassian",
        "primary_affiliation": "Glendale Community College",
        "primary_department": null,
        "all_affiliations": [
            "Glendale Community College"
        ],
        "all_departments": [],
        "perf_states": [
            "CA"
        ],
        "perf_cities": [
            "GLENDALE"
        ],
        "org_names": [
            "Glendale Community College"
        ],
        "org_ueis": [
            "NMBJNJM7TJ24"
        ],
        "inst_types": [
            "university"
        ],
        "emails": [
            "esookiassian@glendale.edu"
        ],
        "roles": [
            "Principal Investigator"
        ],
        "awards": [
            {
                "nsf_award_id": "2515294",
                "title": "Advancing Innovation, Research, and Instruction through Student-Faculty Collaboration and Virtual Reality Integration at a Two-Year College",
                "type": "Standard Grant",
                "tran_type": "Grant",
                "start_date": "2025-08-01",
                "exp_date": "2029-07-31",
                "award_amount": 599739.0,
                "total_amount": 599739.0,
                "is_collaborative": false,
                "co_pi_ids": [],
                "program_elements": [
                    "Innov TwoYear College STEM Ed"
                ],
                "program_codes": [
                    "264Y00"
                ],
                "program_references": [
                    "Improv Undergrad STEM Ed(IUSE)",
                    "UNDERGRADUATE EDUCATION"
                ],
                "program_ref_codes": [
                    "8209",
                    "9178"
                ],
                "dir_abbr": "EDU",
                "div_abbr": "DUE",
                "nsf_directorate": null,
                "fund_division": "Division Of Undergraduate Education",
                "cfda_num": "47.076",
                "po_name": "Suazette Mooring",
                "keywords": [
                    "stem",
                    "student",
                    "college",
                    "community",
                    "through",
                    "faculty",
                    "year",
                    "success",
                    "technology",
                    "students"
                ]
            }
        ],
        "award_count": 1,
        "co_pi_ids": [],
        "program_elements": [
            "Innov TwoYear College STEM Ed"
        ],
        "program_codes": [
            "264Y00"
        ],
        "program_references": [
            "Improv Undergrad STEM Ed(IUSE)",
            "UNDERGRADUATE EDUCATION"
        ],
        "program_ref_codes": [
            "8209",
            "9178"
        ],
        "nsf_directorates": [],
        "dir_abbrs": [
            "EDU"
        ],
        "div_abbrs": [
            "DUE"
        ],
        "fund_divisions": [
            "Division Of Undergraduate Education"
        ],
        "fund_agencies": [
            "NSF"
        ],
        "cfda_nums": [
            "47.076"
        ],
        "program_officers": [
            "Suazette Mooring"
        ],
        "keywords": [
            "stem",
            "student",
            "college",
            "community",
            "through",
            "faculty",
            "year",
            "success",
            "technology",
            "students",
            "across",
            "education",
            "innovation",
            "virtual",
            "reality",
            "integration",
            "aims",
            "colleges",
            "model",
            "effective"
        ],
        "leadership_score": 1,
        "experience_years": 0.55
    },
    "s2_profile": {
        "s2_author_id": "2400422529",
        "name": "Edwin D Sookiassian",
        "affiliations": [],
        "paper_count": 2,
        "citation_count": 0,
        "h_index": 0,
        "papers": [
            {
                "s2_paper_id": "32ce342e2bc90e04f715954006e610912f6345b3",
                "title": "Combined Virtual Reality and Physical Activity Mitigates Mental Workload, Physical Exertion, and Simulator Sickness Compared to Virtual Reality Only in Older Adults",
                "year": 2025,
                "venue": "Alzheimer's & Dementia",
                "citation_count": 0,
                "reference_count": 0,
                "abstract": "Virtual reality (VR) interventions offer immersive cognitive training experiences for older adults; however, challenges such as simulator sickness and cognitive workload can impact participation and adherence. Integrating physical activity, such as stationary cycling, with VR may alleviate these challenges and improve engagement.",
                "authors": [
                    {
                        "s2_author_id": "2276217840",
                        "name": "Cynthia A Nyongesa"
                    },
                    {
                        "s2_author_id": "2338312246",
                        "name": "K. Espejo"
                    },
                    {
                        "s2_author_id": "2338315377",
                        "name": "Marcella Barneclo"
                    },
                    {
                        "s2_author_id": "2400422546",
                        "name": "Emily Ager"
                    },
                    {
                        "s2_author_id": "153102000",
                        "name": "Roshan Ravichandran"
                    },
                    {
                        "s2_author_id": "2400419968",
                        "name": "Adam Gardner"
                    },
                    {
                        "s2_author_id": "2400419400",
                        "name": "Joshua A Fierro"
                    },
                    {
                        "s2_author_id": "2339552453",
                        "name": "Yilei Dong"
                    },
                    {
                        "s2_author_id": "2276214795",
                        "name": "Joanna L Eckhardt"
                    },
                    {
                        "s2_author_id": "2400422529",
                        "name": "Edwin D Sookiassian"
                    },
                    {
                        "s2_author_id": "2246508055",
                        "name": "A. L. Isenberg"
                    },
                    {
                        "s2_author_id": "52215518",
                        "name": "Ashwin Sakhare"
                    },
                    {
                        "s2_author_id": "2268449392",
                        "name": "Judy Pa"
                    }
                ]
            },
            {
                "s2_paper_id": "ff219c365c8adac55cd338a6e4ecbc64093517ef",
                "title": "Combined Virtual Reality and Physical Activity Mitigates Mental Workload, Physical Exertion, and Simulator Sickness Compared to Virtual Reality Only in Older Adults",
                "year": 2025,
                "venue": "Alzheimer's & Dementia",
                "citation_count": 0,
                "reference_count": 0,
                "abstract": "Virtual reality (VR) interventions offer immersive cognitive training experiences for older adults; however, challenges such as simulator sickness and cognitive workload can impact participation and adherence. Integrating physical activity, such as stationary cycling, with VR may alleviate these challenges and improve engagement.",
                "authors": [
                    {
                        "s2_author_id": "2276217840",
                        "name": "Cynthia A Nyongesa"
                    },
                    {
                        "s2_author_id": "2338312246",
                        "name": "K. Espejo"
                    },
                    {
                        "s2_author_id": "2338315377",
                        "name": "Marcella Barneclo"
                    },
                    {
                        "s2_author_id": "2400422546",
                        "name": "Emily Ager"
                    },
                    {
                        "s2_author_id": "153102000",
                        "name": "Roshan Ravichandran"
                    },
                    {
                        "s2_author_id": "2400419968",
                        "name": "Adam Gardner"
                    },
                    {
                        "s2_author_id": "2400419400",
                        "name": "Joshua A Fierro"
                    },
                    {
                        "s2_author_id": "2339552453",
                        "name": "Yilei Dong"
                    },
                    {
                        "s2_author_id": "2276214795",
                        "name": "Joanna L Eckhardt"
                    },
                    {
                        "s2_author_id": "2400422529",
                        "name": "Edwin D Sookiassian"
                    },
                    {
                        "s2_author_id": "2246508055",
                        "name": "A. L. Isenberg"
                    },
                    {
                        "s2_author_id": "52215518",
                        "name": "Ashwin Sakhare"
                    },
                    {
                        "s2_author_id": "2268449392",
                        "name": "Judy Pa"
                    }
                ]
            }
        ],
        "co_authors": [
            {
                "s2_author_id": "2276217840",
                "name": "Cynthia A Nyongesa"
            },
            {
                "s2_author_id": "2338312246",
                "name": "K. Espejo"
            },
            {
                "s2_author_id": "2338315377",
                "name": "Marcella Barneclo"
            },
            {
                "s2_author_id": "2400422546",
                "name": "Emily Ager"
            },
            {
                "s2_author_id": "153102000",
                "name": "Roshan Ravichandran"
            },
            {
                "s2_author_id": "2400419968",
                "name": "Adam Gardner"
            },
            {
                "s2_author_id": "2400419400",
                "name": "Joshua A Fierro"
            },
            {
                "s2_author_id": "2339552453",
                "name": "Yilei Dong"
            },
            {
                "s2_author_id": "2276214795",
                "name": "Joanna L Eckhardt"
            },
            {
                "s2_author_id": "2246508055",
                "name": "A. L. Isenberg"
            },
            {
                "s2_author_id": "52215518",
                "name": "Ashwin Sakhare"
            },
            {
                "s2_author_id": "2268449392",
                "name": "Judy Pa"
            }
        ],
        "total_co_authors": 12,
        "papers_retrieved": 2
    }
}