{
    "nsf_profile": {
        "nsf_pi_id": "000318921",
        "name": "Stefan Richter",
        "primary_affiliation": "University of Tennessee Knoxville",
        "primary_department": null,
        "all_affiliations": [
            "University of Tennessee Knoxville"
        ],
        "all_departments": [],
        "perf_states": [
            "TN"
        ],
        "perf_cities": [
            "KNOXVILLE"
        ],
        "org_names": [
            "University of Tennessee Knoxville"
        ],
        "org_ueis": [
            "FN2YCS2YAUW3"
        ],
        "inst_types": [
            "university"
        ],
        "emails": [
            "srichter@tennessee.edu"
        ],
        "roles": [
            "Principal Investigator"
        ],
        "awards": [
            {
                "nsf_award_id": "2452931",
                "title": "Conference: Hilbert Function Spaces 2025",
                "type": "Standard Grant",
                "tran_type": "Grant",
                "start_date": "2025-06-01",
                "exp_date": "2026-05-31",
                "award_amount": 30000.0,
                "total_amount": 30000.0,
                "is_collaborative": false,
                "co_pi_ids": [],
                "program_elements": [
                    "ANALYSIS PROGRAM"
                ],
                "program_codes": [
                    "128100"
                ],
                "program_references": [
                    "CONFERENCE AND WORKSHOPS"
                ],
                "program_ref_codes": [
                    "7556"
                ],
                "dir_abbr": "MPS",
                "div_abbr": "DMS",
                "nsf_directorate": null,
                "fund_division": "Division Of Mathematical Sciences",
                "cfda_num": "47.049",
                "po_name": "Wing Suet Li",
                "keywords": [
                    "conference",
                    "function",
                    "theory",
                    "analysis",
                    "hilbert",
                    "spaces",
                    "field",
                    "operator",
                    "participants",
                    "home"
                ]
            }
        ],
        "award_count": 1,
        "co_pi_ids": [],
        "program_elements": [
            "ANALYSIS PROGRAM"
        ],
        "program_codes": [
            "128100"
        ],
        "program_references": [
            "CONFERENCE AND WORKSHOPS"
        ],
        "program_ref_codes": [
            "7556"
        ],
        "nsf_directorates": [],
        "dir_abbrs": [
            "MPS"
        ],
        "div_abbrs": [
            "DMS"
        ],
        "fund_divisions": [
            "Division Of Mathematical Sciences"
        ],
        "fund_agencies": [
            "NSF"
        ],
        "cfda_nums": [
            "47.049"
        ],
        "program_officers": [
            "Wing Suet Li"
        ],
        "keywords": [
            "conference",
            "function",
            "theory",
            "analysis",
            "hilbert",
            "spaces",
            "field",
            "operator",
            "participants",
            "home",
            "mathematics",
            "important",
            "devices",
            "held",
            "june",
            "july",
            "frascati",
            "italy",
            "facility",
            "belongs"
        ],
        "leadership_score": 1,
        "experience_years": 0.71
    },
    "s2_profile": {
        "s2_author_id": "48736862",
        "name": "Stefan Richter",
        "affiliations": [],
        "paper_count": 25,
        "citation_count": 323,
        "h_index": 10,
        "papers": [
            {
                "s2_paper_id": "fc735a5c7d3b41bf86e93bd59ce2d0f4b5b6795c",
                "title": "Pipe Flow Development and Transition in CoSmaPipe Facility",
                "year": 2023,
                "venue": "Pamm",
                "citation_count": 0,
                "reference_count": 9,
                "abstract": "The current research focuses on understanding the transition of pipe flow by using a triggering device. In particular, a transition rod was installed within the CoSma\u2010Pipe at the Brandenburg University of Technology Cottbus\u2010Senftenberg. The effect of the transition rod, which has a variable height perpendicular to the axis at the pipe inlet, was examined in a range of 2,500 \u2264 Re \u2264 31,000 where Re is the Reynolds number based on the mean velocity, the diameter, and the air's viscosity. This study used constant temperature hot\u2010wire anemometry to measure the flow. The observed effect of the transition rod was compared to previously published work in which a ring obstacle was used. The main objective of this research is to improve our understanding of the transition of pipe flow by using a triggering device such as the transition rod. By studying the effect of the transition rod on the flow, researchers can gain valuable insights into the dynamics of the transition from laminar to turbulent flow and its implications for various practical applications. This could ultimately lead to the development of more effective ways of controlling and mitigating turbulence in piping systems, engines, turbines, and other applications.",
                "authors": [
                    {
                        "s2_author_id": "48736862",
                        "name": "S. Richter"
                    },
                    {
                        "s2_author_id": "144112986",
                        "name": "E. Zanoun"
                    },
                    {
                        "s2_author_id": "47753225",
                        "name": "J. Peixinho"
                    },
                    {
                        "s2_author_id": "2980448",
                        "name": "C. Egbers"
                    }
                ]
            },
            {
                "s2_paper_id": "1af5a48c68a0fa8af5ef5b367a2ff8275a9aed78",
                "title": "Interfacing photonic building blocks for silicon nitride photonic-integrated circuit-based sensing devices",
                "year": 2022,
                "venue": "Optical Interconnects XXII",
                "citation_count": 0,
                "reference_count": 0,
                "abstract": null,
                "authors": [
                    {
                        "s2_author_id": "7833980",
                        "name": "R. Hainberger"
                    },
                    {
                        "s2_author_id": "50452356",
                        "name": "P. Muellner"
                    },
                    {
                        "s2_author_id": "13682917",
                        "name": "S. Nevlacsil"
                    },
                    {
                        "s2_author_id": "12273129",
                        "name": "M. Eggeling"
                    },
                    {
                        "s2_author_id": "22669288",
                        "name": "F. Vogelbacher"
                    },
                    {
                        "s2_author_id": "47675642",
                        "name": "M. Sagmeister"
                    },
                    {
                        "s2_author_id": "48793482",
                        "name": "G. Meinhardt"
                    },
                    {
                        "s2_author_id": "3104111",
                        "name": "K. Rohracher"
                    },
                    {
                        "s2_author_id": "81320574",
                        "name": "S. Jessenig"
                    },
                    {
                        "s2_author_id": "2157564469",
                        "name": "Desiree Rist"
                    },
                    {
                        "s2_author_id": "13234374",
                        "name": "D. Morecroft"
                    },
                    {
                        "s2_author_id": "145923241",
                        "name": "J. Kraft"
                    },
                    {
                        "s2_author_id": "3156525",
                        "name": "N. Verwaal"
                    },
                    {
                        "s2_author_id": "51162373",
                        "name": "Leonhard Klein"
                    },
                    {
                        "s2_author_id": "2157557920",
                        "name": "Matthias Voelker"
                    },
                    {
                        "s2_author_id": "80960159",
                        "name": "M. Jezzini"
                    },
                    {
                        "s2_author_id": "35210090",
                        "name": "P. Morrissey"
                    },
                    {
                        "s2_author_id": "2067285626",
                        "name": "Peter O'Brien"
                    },
                    {
                        "s2_author_id": "49634533",
                        "name": "S. Gloor"
                    },
                    {
                        "s2_author_id": "2411153",
                        "name": "M. Duelk"
                    },
                    {
                        "s2_author_id": "48736862",
                        "name": "S. Richter"
                    },
                    {
                        "s2_author_id": "49340264",
                        "name": "M. Kempe"
                    },
                    {
                        "s2_author_id": "153624419",
                        "name": "E. Rank"
                    },
                    {
                        "s2_author_id": "3167983",
                        "name": "W. Drexler"
                    }
                ]
            },
            {
                "s2_paper_id": "06d10a2b8819c2ddac88a243b60177a6455c1a3c",
                "title": "Investigation of Large Scale Motion Interaction with the Near\u2010Wall Turbulence",
                "year": 2021,
                "venue": "Pamm",
                "citation_count": 0,
                "reference_count": 3,
                "abstract": "The main objective of the current work is to better understand the interaction of pipe flow large\u2010scale structures in the outer region with the near\u2010wall turbulence. To do so, a decomposition of velocity fluctuating signals has been adopted. Thus, the streamwise velocity fluctuation has been measured for three Reynolds numbers using two pipes located at the Brandenburg University of Technology (BTU). Three Reynolds numbers, Reb \u2248 6 \u00d7 104, Reb \u2248 105 and at Reb \u2248 6 \u00d7 105, have been examined, where Reb is the Reynolds number based on the bulk velocity (Ub), the pipe diameter (D) and the kinematic viscosity (\u03bd). For both pipe facilities, constant temperature hot\u2010wire anemometry has been utilized. The comparison of those three cases addresses the low and high Reynolds number effects on the structures of the outer and the inner regions of the pipe flow. Subsequently, Reynolds\u2010number scaling for such structures and their interaction with the buffer\u2010layer turbulence will be examined.",
                "authors": [
                    {
                        "s2_author_id": "48736862",
                        "name": "S. Richter"
                    },
                    {
                        "s2_author_id": "144112986",
                        "name": "E. Zanoun"
                    },
                    {
                        "s2_author_id": "2980448",
                        "name": "C. Egbers"
                    }
                ]
            },
            {
                "s2_paper_id": "98bc48fc18397be9b8c881ca60d0ab4136ed3974",
                "title": "Porous SiO2 Nanospheres Modified with ZrO2 and Their Use in One-Pot Catalytic Processes to Obtain Value-Added Chemicals from Furfural",
                "year": 2021,
                "venue": "Industrial & Engineering Chemistry Research",
                "citation_count": 21,
                "reference_count": 72,
                "abstract": "Porous SiO2 nanospheres were modified with different loadings of ZrO2 to obtain catalysts with a Si/Zr molar ratio from 2.5 to 30. These materials were characterized by X-ray diffraction, transmission and scanning electron microscopies, N2 adsorption\u2013desorption at \u2212196 \u00b0C, X-ray photoelectron spectroscopy and pyridine and 2\u20136-dimethylpyridine thermoprogrammed desorption. The characterization of these catalysts has revealed that a high proportion of Zr favors the formation of Lewis acid sites, which are implied in catalytic transfer hydrogenation processes, whereas the low Br\u00f6nsted acidity promotes a dehydration reaction, being possible to give rise to a large variety of products from furfural through consecutive reactions, such as furfuryl alcohol, i-propyl furfuryl ether, i-propyl levulinate, and \u03b3-valerolactone, in a range of temperature of 110\u2013170 \u00b0C and 1\u20136 h of reaction.",
                "authors": [
                    {
                        "s2_author_id": "1475327344",
                        "name": "R. Maderuelo-Solera"
                    },
                    {
                        "s2_author_id": "48736862",
                        "name": "S. Richter"
                    },
                    {
                        "s2_author_id": "1422193898",
                        "name": "C. P. Jim\u00e9nez\u2010G\u00f3mez"
                    },
                    {
                        "s2_author_id": "1399705238",
                        "name": "C. Garc\u00eda\u2010Sancho"
                    },
                    {
                        "s2_author_id": "1412836671",
                        "name": "F. J. Garc\u00eda-Mateos"
                    },
                    {
                        "s2_author_id": "91934797",
                        "name": "J. Rosas"
                    },
                    {
                        "s2_author_id": "1402353048",
                        "name": "R. Moreno\u2010Tost"
                    },
                    {
                        "s2_author_id": "14347358",
                        "name": "J. A. Cecilia"
                    },
                    {
                        "s2_author_id": "1403083065",
                        "name": "P. Maireles-Torres"
                    }
                ]
            },
            {
                "s2_paper_id": "073a406ba0e74825bbbd04d54e4ef9a2b678d671",
                "title": "Meshing behaviour of miniaturised plastic gear pairs for power transmission using FEM",
                "year": 2011,
                "venue": "",
                "citation_count": 1,
                "reference_count": 21,
                "abstract": null,
                "authors": [
                    {
                        "s2_author_id": "14826629",
                        "name": "S. Fraulob"
                    },
                    {
                        "s2_author_id": "94322313",
                        "name": "J. Schirmer"
                    },
                    {
                        "s2_author_id": "48736862",
                        "name": "S. Richter"
                    },
                    {
                        "s2_author_id": "145707691",
                        "name": "T. Nagel"
                    }
                ]
            },
            {
                "s2_paper_id": "4032a3d7110e17d6216004a2535f5ec2f70568e1",
                "title": "Development of Highly Reliable Piezo Multilayer Actuators and Lifetime Tests under DC and AC Operating Conditions",
                "year": 2010,
                "venue": "",
                "citation_count": 4,
                "reference_count": 10,
                "abstract": null,
                "authors": [
                    {
                        "s2_author_id": "72462983",
                        "name": "P. Pertsch"
                    },
                    {
                        "s2_author_id": "102759911",
                        "name": "B. Broich"
                    },
                    {
                        "s2_author_id": "151440989",
                        "name": "R. Block"
                    },
                    {
                        "s2_author_id": "48736862",
                        "name": "S. Richter"
                    },
                    {
                        "s2_author_id": "144709602",
                        "name": "E. Hennig"
                    }
                ]
            },
            {
                "s2_paper_id": "5eee9d77f46ecabef0ffe0c2f2fac49c849f12bb",
                "title": "Lateral buckling of continuous steel beams with hinges",
                "year": 2010,
                "venue": "",
                "citation_count": 0,
                "reference_count": 4,
                "abstract": null,
                "authors": [
                    {
                        "s2_author_id": "95317480",
                        "name": "P. Osterrieder"
                    },
                    {
                        "s2_author_id": "48736862",
                        "name": "S. Richter"
                    },
                    {
                        "s2_author_id": "2059823278",
                        "name": "M. Friedrich"
                    }
                ]
            },
            {
                "s2_paper_id": "e30ffeddd347a889e19672273a73dd9dda59cdda",
                "title": "Polymer composite strain sensor based on dielectrophoretically aligned tellurium nanorods",
                "year": 2009,
                "venue": "",
                "citation_count": 10,
                "reference_count": 10,
                "abstract": null,
                "authors": [
                    {
                        "s2_author_id": "30557684",
                        "name": "A. Nocke"
                    },
                    {
                        "s2_author_id": "48736862",
                        "name": "S. Richter"
                    },
                    {
                        "s2_author_id": "144192063",
                        "name": "M. Wolf"
                    },
                    {
                        "s2_author_id": "1384210790",
                        "name": "G. Gerlach"
                    }
                ]
            },
            {
                "s2_paper_id": "c8b6860f3f377df87c65e8728fb12c7ee5e9c67b",
                "title": "Aluminum oxide film as gate dielectric for organic FETs: Anodization and characterization",
                "year": 2008,
                "venue": "",
                "citation_count": 16,
                "reference_count": 24,
                "abstract": null,
                "authors": [
                    {
                        "s2_author_id": "92094835",
                        "name": "X. Dang"
                    },
                    {
                        "s2_author_id": "21069527",
                        "name": "W. Plieth"
                    },
                    {
                        "s2_author_id": "48736862",
                        "name": "S. Richter"
                    },
                    {
                        "s2_author_id": "92445685",
                        "name": "M. Pl\u00f6tner"
                    },
                    {
                        "s2_author_id": "145420050",
                        "name": "W. Fischer"
                    }
                ]
            },
            {
                "s2_paper_id": "8417664b10c3f8a21ecb0b4fd508b26de162f866",
                "title": "RELIABILITY OF PIEZOELECTRIC MULTILAYER ACTUA- TORS",
                "year": 2006,
                "venue": "",
                "citation_count": 19,
                "reference_count": 2,
                "abstract": null,
                "authors": [
                    {
                        "s2_author_id": "72462983",
                        "name": "P. Pertsch"
                    },
                    {
                        "s2_author_id": "48736862",
                        "name": "S. Richter"
                    },
                    {
                        "s2_author_id": "91785670",
                        "name": "D. Kopsch"
                    },
                    {
                        "s2_author_id": "2061096620",
                        "name": "N. Kr\u00e4mer"
                    },
                    {
                        "s2_author_id": "144709602",
                        "name": "E. Hennig"
                    }
                ]
            },
            {
                "s2_paper_id": "cdba49c727ed55feba6b0235467a725ad8572c82",
                "title": "Properties of PZT Multilayer Actuators",
                "year": 2006,
                "venue": "",
                "citation_count": 2,
                "reference_count": 0,
                "abstract": null,
                "authors": [
                    {
                        "s2_author_id": "113638285",
                        "name": "A. Heinzmann"
                    },
                    {
                        "s2_author_id": "144709602",
                        "name": "E. Hennig"
                    },
                    {
                        "s2_author_id": "11296732",
                        "name": "B. Kolle"
                    },
                    {
                        "s2_author_id": "91785670",
                        "name": "D. Kopsch"
                    },
                    {
                        "s2_author_id": "48736862",
                        "name": "S. Richter"
                    },
                    {
                        "s2_author_id": "13898248",
                        "name": "H. Schwotzer"
                    },
                    {
                        "s2_author_id": "98214713",
                        "name": "E. Wehrsdorfer"
                    }
                ]
            },
            {
                "s2_paper_id": "1b797adac2d68850ad11f53efb1a39c30aba0838",
                "title": "Experiments with organic field effect transistors based on polythiophene and thiophene oligomers",
                "year": 2005,
                "venue": "",
                "citation_count": 15,
                "reference_count": 17,
                "abstract": null,
                "authors": [
                    {
                        "s2_author_id": "143854744",
                        "name": "P. T. Nguyen"
                    },
                    {
                        "s2_author_id": "70186239",
                        "name": "U. Rammelt"
                    },
                    {
                        "s2_author_id": "21069527",
                        "name": "W. Plieth"
                    },
                    {
                        "s2_author_id": "48736862",
                        "name": "S. Richter"
                    },
                    {
                        "s2_author_id": "92445685",
                        "name": "M. Pl\u00f6tner"
                    },
                    {
                        "s2_author_id": "145420050",
                        "name": "W. Fischer"
                    },
                    {
                        "s2_author_id": "30802855",
                        "name": "N. Kiriy"
                    },
                    {
                        "s2_author_id": "95465829",
                        "name": "K. P. Kamloth"
                    },
                    {
                        "s2_author_id": "113607184",
                        "name": "H. Adler"
                    }
                ]
            },
            {
                "s2_paper_id": "e5a2218b62b521c68b595e90e5e3eadaed801c43",
                "title": "Development of organic thin film transistors based on flexible substrates",
                "year": 2005,
                "venue": "",
                "citation_count": 11,
                "reference_count": 9,
                "abstract": null,
                "authors": [
                    {
                        "s2_author_id": "48736862",
                        "name": "S. Richter"
                    },
                    {
                        "s2_author_id": "2074314878",
                        "name": "M. Ploetner"
                    },
                    {
                        "s2_author_id": "145420050",
                        "name": "W. Fischer"
                    },
                    {
                        "s2_author_id": "2107764619",
                        "name": "M. Schneider"
                    },
                    {
                        "s2_author_id": "143854744",
                        "name": "P. T. Nguyen"
                    },
                    {
                        "s2_author_id": "21069527",
                        "name": "W. Plieth"
                    },
                    {
                        "s2_author_id": "30802855",
                        "name": "N. Kiriy"
                    },
                    {
                        "s2_author_id": "113607184",
                        "name": "H. Adler"
                    }
                ]
            },
            {
                "s2_paper_id": "7518f7834ffbbad122933061fbc016aec53835e7",
                "title": "Investigation of ink-jet printing of poly-3-octylthiophene for organic field-effect transistors from different solutions",
                "year": 2004,
                "venue": "",
                "citation_count": 39,
                "reference_count": 9,
                "abstract": null,
                "authors": [
                    {
                        "s2_author_id": "92445685",
                        "name": "M. Pl\u00f6tner"
                    },
                    {
                        "s2_author_id": "82806964",
                        "name": "T. Wegener"
                    },
                    {
                        "s2_author_id": "48736862",
                        "name": "S. Richter"
                    },
                    {
                        "s2_author_id": "94807173",
                        "name": "S. Howitz"
                    },
                    {
                        "s2_author_id": "145420050",
                        "name": "W. Fischer"
                    }
                ]
            },
            {
                "s2_paper_id": "bd1ce15fb4e28b725a5241c6d59bf50cbf1c0074",
                "title": "A process for producing a monolithic multilayer (1) consisting of a piezo ceramic or elektrorestriktivt material, as well as the external electrical contact",
                "year": 2003,
                "venue": "",
                "citation_count": 0,
                "reference_count": 0,
                "abstract": null,
                "authors": [
                    {
                        "s2_author_id": "113638285",
                        "name": "A. Heinzmann"
                    },
                    {
                        "s2_author_id": "144709602",
                        "name": "E. Hennig"
                    },
                    {
                        "s2_author_id": "91785670",
                        "name": "D. Kopsch"
                    },
                    {
                        "s2_author_id": "72462983",
                        "name": "P. Pertsch"
                    },
                    {
                        "s2_author_id": "48736862",
                        "name": "S. Richter"
                    },
                    {
                        "s2_author_id": "98214713",
                        "name": "E. Wehrsdorfer"
                    }
                ]
            },
            {
                "s2_paper_id": "db8bffa3e9e6f38a0893569b265f33326f237630",
                "title": "Microfluidic Devices on Printed Circuit Board",
                "year": 2002,
                "venue": "",
                "citation_count": 5,
                "reference_count": 22,
                "abstract": null,
                "authors": [
                    {
                        "s2_author_id": "48736862",
                        "name": "S. Richter"
                    },
                    {
                        "s2_author_id": "49693902",
                        "name": "N. Nguyen"
                    },
                    {
                        "s2_author_id": "51962420",
                        "name": "A. Wego"
                    },
                    {
                        "s2_author_id": "11999341",
                        "name": "L. Pagel"
                    }
                ]
            },
            {
                "s2_paper_id": "0a00da9d17a0e76c718c6b059710bed6ebcbabb0",
                "title": "Investigations on thermo-pneumatic volume actuators based on PCB technology",
                "year": 2001,
                "venue": "",
                "citation_count": 50,
                "reference_count": 7,
                "abstract": null,
                "authors": [
                    {
                        "s2_author_id": "51962420",
                        "name": "A. Wego"
                    },
                    {
                        "s2_author_id": "117689203",
                        "name": "H. Glock"
                    },
                    {
                        "s2_author_id": "11999341",
                        "name": "L. Pagel"
                    },
                    {
                        "s2_author_id": "48736862",
                        "name": "S. Richter"
                    }
                ]
            },
            {
                "s2_paper_id": "132bfaad1276b8ff3582e88c6ba50ac1826b0bdb",
                "title": "Fluidic microsystems based on printed circuit board technology",
                "year": 2001,
                "venue": "",
                "citation_count": 75,
                "reference_count": 9,
                "abstract": null,
                "authors": [
                    {
                        "s2_author_id": "51962420",
                        "name": "A. Wego"
                    },
                    {
                        "s2_author_id": "48736862",
                        "name": "S. Richter"
                    },
                    {
                        "s2_author_id": "11999341",
                        "name": "L. Pagel"
                    }
                ]
            },
            {
                "s2_paper_id": "2dc484b44f5b643de87b6658adbeb4daa20a5adf",
                "title": "Fast military surface vessel",
                "year": 2001,
                "venue": "",
                "citation_count": 0,
                "reference_count": 0,
                "abstract": null,
                "authors": [
                    {
                        "s2_author_id": "100592007",
                        "name": "A. Drefs"
                    },
                    {
                        "s2_author_id": "48736862",
                        "name": "S. Richter"
                    },
                    {
                        "s2_author_id": "10188150",
                        "name": "Karl-Otto Sadler"
                    },
                    {
                        "s2_author_id": "72953534",
                        "name": "R. Hartig"
                    },
                    {
                        "s2_author_id": "30581056",
                        "name": "W. Rzadki"
                    }
                ]
            },
            {
                "s2_paper_id": "e44e80071a1e7a4aa9188ec8e9f2c828f84f583d",
                "title": "Drives for ships",
                "year": 2001,
                "venue": "",
                "citation_count": 0,
                "reference_count": 0,
                "abstract": null,
                "authors": [
                    {
                        "s2_author_id": "72953534",
                        "name": "R. Hartig"
                    },
                    {
                        "s2_author_id": "48736862",
                        "name": "S. Richter"
                    },
                    {
                        "s2_author_id": "30581056",
                        "name": "W. Rzadki"
                    },
                    {
                        "s2_author_id": "100592007",
                        "name": "A. Drefs"
                    },
                    {
                        "s2_author_id": "145480723",
                        "name": "R. Reuter"
                    },
                    {
                        "s2_author_id": "51031882",
                        "name": "M. Heer"
                    },
                    {
                        "s2_author_id": "101101336",
                        "name": "Stephan Brabeck"
                    }
                ]
            },
            {
                "s2_paper_id": "f66f0f99a2012a5be41b721b78d1855048844aa1",
                "title": "A process for producing a monolithic piezoceramic multilayer actuators and monolithic piezoceramic multilayer actuator",
                "year": 2000,
                "venue": "",
                "citation_count": 0,
                "reference_count": 0,
                "abstract": null,
                "authors": [
                    {
                        "s2_author_id": "48736862",
                        "name": "S. Richter"
                    }
                ]
            },
            {
                "s2_paper_id": "fcadbf0c794848cea0a12f7d1b66003818dac3a9",
                "title": "A NEW CONCEPT FOR PLATE BUCKLING DESIGN OF CRANE RUNWAY GIRDERS",
                "year": 2000,
                "venue": "",
                "citation_count": 0,
                "reference_count": 0,
                "abstract": null,
                "authors": [
                    {
                        "s2_author_id": "95317480",
                        "name": "P. Osterrieder"
                    },
                    {
                        "s2_author_id": "48736862",
                        "name": "S. Richter"
                    },
                    {
                        "s2_author_id": "2061465041",
                        "name": "F. Werner"
                    }
                ]
            },
            {
                "s2_paper_id": "1bb32d85d84e8cd6346dbbb851e8f2a4d7111a8c",
                "title": "Hybrid micro dosing system",
                "year": 1998,
                "venue": "",
                "citation_count": 0,
                "reference_count": 0,
                "abstract": null,
                "authors": [
                    {
                        "s2_author_id": "49693902",
                        "name": "N. Nguyen"
                    },
                    {
                        "s2_author_id": "48736862",
                        "name": "S. Richter"
                    },
                    {
                        "s2_author_id": "50493822",
                        "name": "J. Mehner"
                    },
                    {
                        "s2_author_id": "50655962",
                        "name": "S. Schubert"
                    },
                    {
                        "s2_author_id": "2529961",
                        "name": "W. D\u00f6tzel"
                    },
                    {
                        "s2_author_id": "144727439",
                        "name": "T. Gessner"
                    }
                ]
            },
            {
                "s2_paper_id": "7086f364980a997672858dd7d779253754616650",
                "title": "Hybrid microdosing system",
                "year": 1998,
                "venue": "Photonics West - Micro and Nano Fabricated Electromechanical and Optical Components",
                "citation_count": 1,
                "reference_count": 0,
                "abstract": null,
                "authors": [
                    {
                        "s2_author_id": "2351989",
                        "name": "Nam-Trung Nguyen"
                    },
                    {
                        "s2_author_id": "48736862",
                        "name": "S. Richter"
                    },
                    {
                        "s2_author_id": "50493822",
                        "name": "J. Mehner"
                    },
                    {
                        "s2_author_id": "50655962",
                        "name": "S. Schubert"
                    },
                    {
                        "s2_author_id": "2097208921",
                        "name": "W. Doetzel"
                    },
                    {
                        "s2_author_id": "144727439",
                        "name": "T. Gessner"
                    }
                ]
            },
            {
                "s2_paper_id": "acc052f880cf84b1e6145345454dd7b99e47d429",
                "title": "Hybrid-assembled micro dosing system using silicon-based micropump/ valve and mass flow sensor",
                "year": 1998,
                "venue": "",
                "citation_count": 54,
                "reference_count": 20,
                "abstract": null,
                "authors": [
                    {
                        "s2_author_id": "49693902",
                        "name": "N. Nguyen"
                    },
                    {
                        "s2_author_id": "50655962",
                        "name": "S. Schubert"
                    },
                    {
                        "s2_author_id": "48736862",
                        "name": "S. Richter"
                    },
                    {
                        "s2_author_id": "2529961",
                        "name": "W. D\u00f6tzel"
                    }
                ]
            }
        ],
        "co_authors": [
            {
                "s2_author_id": "144112986",
                "name": "E. Zanoun"
            },
            {
                "s2_author_id": "47753225",
                "name": "J. Peixinho"
            },
            {
                "s2_author_id": "2980448",
                "name": "C. Egbers"
            },
            {
                "s2_author_id": "7833980",
                "name": "R. Hainberger"
            },
            {
                "s2_author_id": "50452356",
                "name": "P. Muellner"
            },
            {
                "s2_author_id": "13682917",
                "name": "S. Nevlacsil"
            },
            {
                "s2_author_id": "12273129",
                "name": "M. Eggeling"
            },
            {
                "s2_author_id": "22669288",
                "name": "F. Vogelbacher"
            },
            {
                "s2_author_id": "47675642",
                "name": "M. Sagmeister"
            },
            {
                "s2_author_id": "48793482",
                "name": "G. Meinhardt"
            },
            {
                "s2_author_id": "3104111",
                "name": "K. Rohracher"
            },
            {
                "s2_author_id": "81320574",
                "name": "S. Jessenig"
            },
            {
                "s2_author_id": "2157564469",
                "name": "Desiree Rist"
            },
            {
                "s2_author_id": "13234374",
                "name": "D. Morecroft"
            },
            {
                "s2_author_id": "145923241",
                "name": "J. Kraft"
            },
            {
                "s2_author_id": "3156525",
                "name": "N. Verwaal"
            },
            {
                "s2_author_id": "51162373",
                "name": "Leonhard Klein"
            },
            {
                "s2_author_id": "2157557920",
                "name": "Matthias Voelker"
            },
            {
                "s2_author_id": "80960159",
                "name": "M. Jezzini"
            },
            {
                "s2_author_id": "35210090",
                "name": "P. Morrissey"
            },
            {
                "s2_author_id": "2067285626",
                "name": "Peter O'Brien"
            },
            {
                "s2_author_id": "49634533",
                "name": "S. Gloor"
            },
            {
                "s2_author_id": "2411153",
                "name": "M. Duelk"
            },
            {
                "s2_author_id": "49340264",
                "name": "M. Kempe"
            },
            {
                "s2_author_id": "153624419",
                "name": "E. Rank"
            },
            {
                "s2_author_id": "3167983",
                "name": "W. Drexler"
            },
            {
                "s2_author_id": "1475327344",
                "name": "R. Maderuelo-Solera"
            },
            {
                "s2_author_id": "1422193898",
                "name": "C. P. Jim\u00e9nez\u2010G\u00f3mez"
            },
            {
                "s2_author_id": "1399705238",
                "name": "C. Garc\u00eda\u2010Sancho"
            },
            {
                "s2_author_id": "1412836671",
                "name": "F. J. Garc\u00eda-Mateos"
            },
            {
                "s2_author_id": "91934797",
                "name": "J. Rosas"
            },
            {
                "s2_author_id": "1402353048",
                "name": "R. Moreno\u2010Tost"
            },
            {
                "s2_author_id": "14347358",
                "name": "J. A. Cecilia"
            },
            {
                "s2_author_id": "1403083065",
                "name": "P. Maireles-Torres"
            },
            {
                "s2_author_id": "14826629",
                "name": "S. Fraulob"
            },
            {
                "s2_author_id": "94322313",
                "name": "J. Schirmer"
            },
            {
                "s2_author_id": "145707691",
                "name": "T. Nagel"
            },
            {
                "s2_author_id": "72462983",
                "name": "P. Pertsch"
            },
            {
                "s2_author_id": "102759911",
                "name": "B. Broich"
            },
            {
                "s2_author_id": "151440989",
                "name": "R. Block"
            },
            {
                "s2_author_id": "144709602",
                "name": "E. Hennig"
            },
            {
                "s2_author_id": "95317480",
                "name": "P. Osterrieder"
            },
            {
                "s2_author_id": "2059823278",
                "name": "M. Friedrich"
            },
            {
                "s2_author_id": "30557684",
                "name": "A. Nocke"
            },
            {
                "s2_author_id": "144192063",
                "name": "M. Wolf"
            },
            {
                "s2_author_id": "1384210790",
                "name": "G. Gerlach"
            },
            {
                "s2_author_id": "92094835",
                "name": "X. Dang"
            },
            {
                "s2_author_id": "21069527",
                "name": "W. Plieth"
            },
            {
                "s2_author_id": "92445685",
                "name": "M. Pl\u00f6tner"
            },
            {
                "s2_author_id": "145420050",
                "name": "W. Fischer"
            },
            {
                "s2_author_id": "91785670",
                "name": "D. Kopsch"
            },
            {
                "s2_author_id": "2061096620",
                "name": "N. Kr\u00e4mer"
            },
            {
                "s2_author_id": "113638285",
                "name": "A. Heinzmann"
            },
            {
                "s2_author_id": "11296732",
                "name": "B. Kolle"
            },
            {
                "s2_author_id": "13898248",
                "name": "H. Schwotzer"
            },
            {
                "s2_author_id": "98214713",
                "name": "E. Wehrsdorfer"
            },
            {
                "s2_author_id": "143854744",
                "name": "P. T. Nguyen"
            },
            {
                "s2_author_id": "70186239",
                "name": "U. Rammelt"
            },
            {
                "s2_author_id": "30802855",
                "name": "N. Kiriy"
            },
            {
                "s2_author_id": "95465829",
                "name": "K. P. Kamloth"
            },
            {
                "s2_author_id": "113607184",
                "name": "H. Adler"
            },
            {
                "s2_author_id": "2074314878",
                "name": "M. Ploetner"
            },
            {
                "s2_author_id": "2107764619",
                "name": "M. Schneider"
            },
            {
                "s2_author_id": "82806964",
                "name": "T. Wegener"
            },
            {
                "s2_author_id": "94807173",
                "name": "S. Howitz"
            },
            {
                "s2_author_id": "49693902",
                "name": "N. Nguyen"
            },
            {
                "s2_author_id": "51962420",
                "name": "A. Wego"
            },
            {
                "s2_author_id": "11999341",
                "name": "L. Pagel"
            },
            {
                "s2_author_id": "117689203",
                "name": "H. Glock"
            },
            {
                "s2_author_id": "100592007",
                "name": "A. Drefs"
            },
            {
                "s2_author_id": "10188150",
                "name": "Karl-Otto Sadler"
            },
            {
                "s2_author_id": "72953534",
                "name": "R. Hartig"
            },
            {
                "s2_author_id": "30581056",
                "name": "W. Rzadki"
            },
            {
                "s2_author_id": "145480723",
                "name": "R. Reuter"
            },
            {
                "s2_author_id": "51031882",
                "name": "M. Heer"
            },
            {
                "s2_author_id": "101101336",
                "name": "Stephan Brabeck"
            },
            {
                "s2_author_id": "2061465041",
                "name": "F. Werner"
            },
            {
                "s2_author_id": "50493822",
                "name": "J. Mehner"
            },
            {
                "s2_author_id": "50655962",
                "name": "S. Schubert"
            },
            {
                "s2_author_id": "2529961",
                "name": "W. D\u00f6tzel"
            },
            {
                "s2_author_id": "144727439",
                "name": "T. Gessner"
            },
            {
                "s2_author_id": "2351989",
                "name": "Nam-Trung Nguyen"
            },
            {
                "s2_author_id": "2097208921",
                "name": "W. Doetzel"
            }
        ],
        "total_co_authors": 83,
        "papers_retrieved": 25
    }
}