{
    "nsf_profile": {
        "nsf_pi_id": "000507374",
        "name": "Shi Bai",
        "primary_affiliation": "University of Delaware",
        "primary_department": null,
        "all_affiliations": [
            "University of Delaware"
        ],
        "all_departments": [],
        "perf_states": [
            "DE"
        ],
        "perf_cities": [
            "NEWARK"
        ],
        "org_names": [
            "University of Delaware"
        ],
        "org_ueis": [
            "T72NHKM259N3"
        ],
        "inst_types": [
            "university"
        ],
        "emails": [
            "bais@udel.edu"
        ],
        "roles": [
            "Co-Principal Investigator"
        ],
        "awards": [
            {
                "nsf_award_id": "2509986",
                "title": "Equipment: MRI: Track 2 Acquisition of a 600 MHz Dynamic Nuclear Polarization NMR System for Interdisciplinary Research, Education, and Training",
                "type": "Standard Grant",
                "tran_type": "Grant",
                "start_date": "2025-08-15",
                "exp_date": "2028-07-31",
                "award_amount": 3982009.0,
                "total_amount": 3982009.0,
                "is_collaborative": false,
                "co_pi_ids": [
                    "000164577",
                    "000926199"
                ],
                "program_elements": [
                    "Major Research Instrumentation"
                ],
                "program_codes": [
                    "118900"
                ],
                "program_references": [
                    "MAJOR RESEARCH INSTRUMENTATION",
                    "Biotechnology",
                    "EXP PROG TO STIM COMP RES"
                ],
                "program_ref_codes": [
                    "1189",
                    "8038",
                    "9150"
                ],
                "dir_abbr": "BIO",
                "div_abbr": "DBI",
                "nsf_directorate": null,
                "fund_division": "Division of Biological Infrastructure",
                "cfda_num": "47.074, 47.083",
                "po_name": "Krisztina Varga",
                "keywords": [
                    "nuclear",
                    "scientific",
                    "instrumentation",
                    "dynamic",
                    "polarization",
                    "training",
                    "state",
                    "instrument",
                    "access",
                    "capabilities"
                ]
            }
        ],
        "award_count": 1,
        "co_pi_ids": [
            "000926199",
            "000164577"
        ],
        "program_elements": [
            "Major Research Instrumentation"
        ],
        "program_codes": [
            "118900"
        ],
        "program_references": [
            "MAJOR RESEARCH INSTRUMENTATION",
            "Biotechnology",
            "EXP PROG TO STIM COMP RES"
        ],
        "program_ref_codes": [
            "1189",
            "8038",
            "9150"
        ],
        "nsf_directorates": [],
        "dir_abbrs": [
            "BIO"
        ],
        "div_abbrs": [
            "DBI"
        ],
        "fund_divisions": [
            "Division of Biological Infrastructure"
        ],
        "fund_agencies": [
            "NSF"
        ],
        "cfda_nums": [
            "47.074, 47.083"
        ],
        "program_officers": [
            "Krisztina Varga"
        ],
        "keywords": [
            "nuclear",
            "scientific",
            "instrumentation",
            "dynamic",
            "polarization",
            "training",
            "state",
            "instrument",
            "access",
            "capabilities",
            "development",
            "highly",
            "sciences",
            "biotechnology",
            "major",
            "equipment",
            "track",
            "acquisition",
            "interdisciplinary",
            "education"
        ],
        "leadership_score": 1,
        "experience_years": 0.51
    },
    "s2_profile": {
        "s2_author_id": "49163176",
        "name": "Shi Bai",
        "affiliations": [],
        "paper_count": 21,
        "citation_count": 148,
        "h_index": 7,
        "papers": [
            {
                "s2_paper_id": "1c1acb10afbed903884b06b89f359dc99e66d1af",
                "title": "Research on the Analytical Model of Improved Magnetic Flux Leakage Signal for the Local Stress Concentration Zone of Pipelines",
                "year": 2022,
                "venue": "Italian National Conference on Sensors",
                "citation_count": 9,
                "reference_count": 34,
                "abstract": "Local stress concentrations pose a significant hazard to the safe operation of pipelines. However, the classical analytical model of the magnetic flux leakage (MFL) signal is still unable to effectively quantitatively analyze and accurately evaluate the local stress concentration zone of a pipeline. In this paper, based on the Jiles\u2013Atherton model of the magnetomechanical effect, the mathematical relationship between stress and the magnetization of ferromagnetic material under hysteresis conditions is introduced, and an improved analytical model of the MFL signal based on the magnetomechanical model is established. The influence law of stress intensity on the MFL signal in the local stress concentration zone of the pipeline is calculated and analyzed, and the theoretical calculation results are verified through experiments. Simulation and experimental results show that, considering the hysteresis condition, the stress causes a change in the hysteresis loop of the ferromagnetic material, and the magnetization strength of the material decreases with increasing stress; the effect of stress on the magnetization strength of ferromagnetic materials is most obvious when the external magnetic field is approximately 5 KA/m. The MFL signal on the surface of the local stress concentration zone of the pipe changes abruptly, and the amount of change in the axial amplitude and radial peak-to-peak value of the leakage signal of the pipe tends to increase with the increase in the stress intensity of the local stress concentration zone. A comparison of the analysis with the classical analytical model of the MFL signal shows that the improved analytical model of the MFL signal is more suitable for the quantification study of the local stress concentration zone of the pipeline.",
                "authors": [
                    {
                        "s2_author_id": "48064203",
                        "name": "Lijian Yang"
                    },
                    {
                        "s2_author_id": "2153791522",
                        "name": "Fuyin Zheng"
                    },
                    {
                        "s2_author_id": "2119408411",
                        "name": "Ping Huang"
                    },
                    {
                        "s2_author_id": "49163176",
                        "name": "S. Bai"
                    },
                    {
                        "s2_author_id": "15531317",
                        "name": "Yuming Su"
                    }
                ]
            },
            {
                "s2_paper_id": "7f97830253817ec1f2f458c8444db3f8cd22e39f",
                "title": "Design of multi-frequency electrical impedance tomography system based on multisine excitation and integer-period sampling",
                "year": 2022,
                "venue": "Acta Physica Sinica",
                "citation_count": 2,
                "reference_count": 18,
                "abstract": "Starting from the principle that the integer-period sampling (IPS) of periodic signals is free of spectrum leakage, in this paper we propose the multisine-IPS theory, deduce theoretically the sampling rate setting formula of multisine-IPS condition for the first time, and build its realization method based on field-programmable gate array (FPGA) plus digital-to-analog converter (DAC) plus analog-to-digital converter (ADC). A new multi-frequency electrical impedance tomography (mfEIT) system based on multisine excitation and its IPS theory is developed, and a dual-target imaging model including a carrot stick and a cucumber stick is designed. The experiments of multi-frequency time-difference imaging and frequency-difference imaging are carried out on the mfEIT system. The experimental results show that the newly-designed mfEIT system can achieve full-band impedance measurements on multiple objective tissue boundary at 20 frequency points (2 kHz-997 kHz) within one fundamental period (1 ms), and the structure and position of biological tissues with different electrical properties can also be distinguished from the resulting images. The proposed multisine-IPS theory and its implementation method can complete a full-band impedance measurement within one multisine fundamental period, which lays a theoretical and technical foundation for developing high-speed mfEIT system.",
                "authors": [
                    {
                        "s2_author_id": "119607717",
                        "name": "Yuxiang Yang"
                    },
                    {
                        "s2_author_id": "49163176",
                        "name": "S. Bai"
                    },
                    {
                        "s2_author_id": "2152782186",
                        "name": "Hai Lin"
                    },
                    {
                        "s2_author_id": "2109036715",
                        "name": "Jianmin Li"
                    },
                    {
                        "s2_author_id": "150106477",
                        "name": "Fu Zhang"
                    }
                ]
            },
            {
                "s2_paper_id": "a77154b201a601e8c4acd84de440635435b28aef",
                "title": "A Temperature Imaging Method for Multi-Chip High Power LEDs Based on the Magnetic Nanoparticle Thermometer",
                "year": 2022,
                "venue": "Nanomaterials",
                "citation_count": 2,
                "reference_count": 32,
                "abstract": "In this study, a temperature imaging method based on a magnetic nanoparticle thermometer is proposed and evaluated. We first constructed a new model for finding the single temperature of magnetic nanoparticles with core size distribution. Specifically, we employed an air-core coil as a magnetic probe, which measured the magnetization of magnetic nanoparticles (MNPs). We then constructed a relation between the output signal of an air-core coil in the direction of the geometric center axis and the magnetization of the MNPs in a 2-D imaging area based on the magnetic dipole theory. Once this was achieved, we established a temperature imaging model by utilizing Green function as the convolution kernel, which describes the distance relationship between MNPs and the geometric center axis of the air-cored coil. After this, we calculated the harmonic distribution by a deconvolution algorithm and determined the temperature of the MNPs at different positions based on the model of harmonic amplitude and temperature, resulting in the 2-D temperature distribution. The simulation proved that the model and method of 2-D temperature distribution measurement could theoretically be acceptable. In the experiment, the 2-D temperature distribution of multi-chip power LEDs was measured accurately by a homemade system, thus demonstrating the feasibility of the proposed method for temperature imaging. This method is expected to provide a new solution for measuring the internal temperature distribution of opaque objects under extreme conditions.",
                "authors": [
                    {
                        "s2_author_id": "8640067",
                        "name": "Zhongzhou Du"
                    },
                    {
                        "s2_author_id": "144010725",
                        "name": "B. Hu"
                    },
                    {
                        "s2_author_id": "49188262",
                        "name": "Na Ye"
                    },
                    {
                        "s2_author_id": "2116961203",
                        "name": "Yi Sun"
                    },
                    {
                        "s2_author_id": "2244605509",
                        "name": "Haochen Zhang"
                    },
                    {
                        "s2_author_id": "49163176",
                        "name": "S. Bai"
                    }
                ]
            },
            {
                "s2_paper_id": "b2a2d569b740041caeecb5c5f581837f407bc9ee",
                "title": "Three-Dimensional Numerical Analysis of Wall Stress Induced by Asymmetric Oscillation of Microbubble Trains inside Micro-vessels",
                "year": 2022,
                "venue": "The Physics of Fluids",
                "citation_count": 12,
                "reference_count": 0,
                "abstract": "Understanding the stress patterns produced by microbubbles (MB) in blood vessels is important in enhancing the efficacy and safety of ultrasound-assisted therapy, diagnosis and drug delivery. In this study, the wall stress produced by a non-spherical oscillation of MBs within the lumen of micro-vessels was numerically analyzed using a three-dimensional finite element method. We systematically simulated configurations containing an odd number of bubbles from three to nine, equally spaced along the long axis of the vessel, insonated at an acoustic pressure of 200 kPa. We observed that 3 MBs were sufficient to simulate the stress state of an infinite number of bubbles. As the bubble spacing increased the interaction between them weakened to the point that they could be considered to act independently. In the relationship between stress and acoustic frequency there were differences between the single and 3 MB cases. The stress induced by 3MBs was greater than the single bubble case. When the bubbles were near the wall, the shear stress peak was largely independent of vessel radius, but the circumferential stress peak increased with the radius. This study offers further insight into our understanding of, the magnitude and distribution of stresses produced by multiple ultrasonically excited MBs inside capillaries.",
                "authors": [
                    {
                        "s2_author_id": "2121069982",
                        "name": "J. Ri"
                    },
                    {
                        "s2_author_id": "2048081196",
                        "name": "N. Pang"
                    },
                    {
                        "s2_author_id": "49163176",
                        "name": "S. Bai"
                    },
                    {
                        "s2_author_id": "2146301380",
                        "name": "Jialin Xu"
                    },
                    {
                        "s2_author_id": "2126044645",
                        "name": "Lisheng Xu"
                    },
                    {
                        "s2_author_id": "104224113",
                        "name": "Songchol Ri"
                    },
                    {
                        "s2_author_id": "2152877654",
                        "name": "Yudong Yao"
                    },
                    {
                        "s2_author_id": "31726364",
                        "name": "S. Greenwald"
                    }
                ]
            },
            {
                "s2_paper_id": "3d21f003e2899d7e79d47149389159ef9063aab9",
                "title": "Empirical Expression of AC Susceptibility of Magnetic Nanoparticles and Potential Application in Biosensing",
                "year": 2021,
                "venue": "IEEE Transactions on Nanobioscience",
                "citation_count": 5,
                "reference_count": 22,
                "abstract": "Magnetic nanoparticles (MNPs) have been widely studied for use in biomedical and industrial applications. The frequency dependence of the magnetization of magnetic nanoparticles is analyzed for different AC excitation fields. We employ a Fokker-Planck equation, which accurately describes AC magnetization dynamics and analyze the difference in AC susceptibility between Fokker-Planck equation and Debye model. Based on these results we proposed a simple, empirical AC susceptibility model. Simulation and experimental results showed that the proposed empirical model accurately describes AC susceptibility, and the AC susceptibility constructed with the proposed empirical equation based on Debye model agrees well with the measured results. Therefore, we can utilize the proposed empirical model in biomedical applications, such as the estimation of the hydrodynamic size and temperature, which is expected to apply to biologicals assays and hyperthermia.",
                "authors": [
                    {
                        "s2_author_id": "8640067",
                        "name": "Zhongzhou Du"
                    },
                    {
                        "s2_author_id": "3246432",
                        "name": "YanYing Cui"
                    },
                    {
                        "s2_author_id": "2116961203",
                        "name": "Yi Sun"
                    },
                    {
                        "s2_author_id": null,
                        "name": "Haochen Zhang"
                    },
                    {
                        "s2_author_id": "49163176",
                        "name": "S. Bai"
                    },
                    {
                        "s2_author_id": "1863177",
                        "name": "Takashi Yoshida"
                    }
                ]
            },
            {
                "s2_paper_id": "2cc53cc4c9f80530983b070a285a6f0d8ce302c8",
                "title": "An effective method for differentiating inside and outside defects of oil and gas pipelines based on additional eddy current in low-frequency electromagnetic detection technique",
                "year": 2020,
                "venue": "Japanese Journal of Applied Physics",
                "citation_count": 8,
                "reference_count": 31,
                "abstract": "Accurate differentiation of whether the defect position is located on the inside or outside surface is necessary in the low-frequency electromagnetic detection technique (LFET) on oil and gas pipelines. We design a set of composite probe arrays that consisted of inductive magnetic coils (LFET coils) and eddy current testing (ECT) coils to accomplish comprehensive inspection, meanwhile, the theoretical calculation and analysis of the mutual interference mechanism between LFET and ECT coils were mainly implemented. Experimental result demonstrates that the ECT coils can effectively minimize the low-frequency magnetic field interference and allow low-frequency excitation coil setting parameters to be adjusted in a wide range (760 V Hz of voltage\u2013frequency product in this experiment) to identify the inside defects above 1 mm depth while nothing found to detect outside defects. This circumstance enables the identification of the inside defect of 4 mm wide and 1 mm deep (10% wall thickness) at a lift-off value of 14 mm.",
                "authors": [
                    {
                        "s2_author_id": "48064203",
                        "name": "Lijian Yang"
                    },
                    {
                        "s2_author_id": "152392321",
                        "name": "Ping Huang"
                    },
                    {
                        "s2_author_id": "49163176",
                        "name": "S. Bai"
                    },
                    {
                        "s2_author_id": "9355542",
                        "name": "Song-wei Gao"
                    },
                    {
                        "s2_author_id": "34459020",
                        "name": "T. Sasayama"
                    }
                ]
            },
            {
                "s2_paper_id": "4814c4812ae5064ab959c72e885013edd446abc1",
                "title": "Research on the magnetic flux leakage field distribution characteristics of defect in low-frequency electromagnetic detection technique",
                "year": 2020,
                "venue": "IEICE Electronics Express",
                "citation_count": 6,
                "reference_count": 30,
                "abstract": "This work aimed to investigate the distribution characteristics of the low-frequency magnetic \ufb02ux leakage (LF-MFL) \ufb01eld of defect on oil and gas pipelines in low-frequency electromagnetic detection technique (LFET). Taking four types of crack defects (rectangular, semicircular, trapezoidal, and V-shaped grooves) with equal lengths, widths and di\ufb00erent bottom shapes into consideration, the speci\ufb01c mathematical model of the LF-MFL \ufb01eld was inferred and established on the basis of magnetic dipole theory. Experimental results demonstrated that the variation values of the tangential and normal component upper-lower envelope di\ufb00erence curves werelinearlypositivelycorrelatedwiththedefectcross-sectionalareaalongthedetectiondirection,whichwasstrictlyindependentofbottomshapeandexcitationconditions(amplitude,frequencyandlift-o\ufb00).",
                "authors": [
                    {
                        "s2_author_id": "48064203",
                        "name": "Lijian Yang"
                    },
                    {
                        "s2_author_id": "152392321",
                        "name": "Ping Huang"
                    },
                    {
                        "s2_author_id": "9355542",
                        "name": "Song-wei Gao"
                    },
                    {
                        "s2_author_id": "2044447837",
                        "name": "Zhouzhong Du"
                    },
                    {
                        "s2_author_id": "49163176",
                        "name": "S. Bai"
                    }
                ]
            },
            {
                "s2_paper_id": "679a28ada99285233a04f3e4f6455d6be969578d",
                "title": "Amplitude and phase of higher harmonic of magnetic nanoparticles\u2019 magnetization under low frequency magnetic field",
                "year": 2020,
                "venue": "",
                "citation_count": 1,
                "reference_count": 22,
                "abstract": null,
                "authors": [
                    {
                        "s2_author_id": "8640067",
                        "name": "Zhongzhou Du"
                    },
                    {
                        "s2_author_id": "2116961203",
                        "name": "Yi Sun"
                    },
                    {
                        "s2_author_id": "2155681103",
                        "name": "Dandan Wang"
                    },
                    {
                        "s2_author_id": "103538013",
                        "name": "Oji Higashi"
                    },
                    {
                        "s2_author_id": "49163176",
                        "name": "S. Bai"
                    },
                    {
                        "s2_author_id": "2038374944",
                        "name": "Y. Noguchi"
                    },
                    {
                        "s2_author_id": "2512701",
                        "name": "K. Enpuku"
                    },
                    {
                        "s2_author_id": "1863177",
                        "name": "Takashi Yoshida"
                    }
                ]
            },
            {
                "s2_paper_id": "78a8defbfe8a5b94a7d286fbe3b38b5d23c08758",
                "title": "Empirical Expression for AC Magnetization Harmonics of Magnetic Nanoparticles under High-Frequency Excitation Field for Thermometry",
                "year": 2020,
                "venue": "Nanomaterials",
                "citation_count": 3,
                "reference_count": 23,
                "abstract": "The Fokker\u2013Planck equation accurately describes AC magnetization dynamics of magnetic nanoparticles (MNPs). However, the model for describing AC magnetization dynamics of MNPs based on Fokker-Planck equation is very complicated and the numerical calculation of Fokker-Planck function is time consuming. In the stable stage of AC magnetization response, there are differences in the harmonic phase and amplitude between the stable magnetization response of MNPs described by Langevin and Fokker\u2013Planck equation. Therefore, we proposed an empirical model for AC magnetization harmonics to compensate the attenuation of harmonics amplitude induced by a high frequency excitation field. Simulation and experimental results show that the proposed model accurately describes the AC M\u2013H curve. Moreover, we propose a harmonic amplitude\u2013temperature model of a magnetic nanoparticle thermometer (MNPT) in a high-frequency excitation field. The simulation results show that the temperature error is less than 0.008 K in the temperature range 310\u2013320 K. The proposed empirical model is expected to help improve MNPT performance.",
                "authors": [
                    {
                        "s2_author_id": "8640067",
                        "name": "Zhongzhou Du"
                    },
                    {
                        "s2_author_id": "2155681103",
                        "name": "Dandan Wang"
                    },
                    {
                        "s2_author_id": "2116961203",
                        "name": "Yi Sun"
                    },
                    {
                        "s2_author_id": "2038374944",
                        "name": "Y. Noguchi"
                    },
                    {
                        "s2_author_id": "49163176",
                        "name": "S. Bai"
                    },
                    {
                        "s2_author_id": "1863177",
                        "name": "Takashi Yoshida"
                    }
                ]
            },
            {
                "s2_paper_id": "c3bd0b01ccff0570193ae037c90ae5837afa7c89",
                "title": "An Improved Method for Estimating Core Size Distributions of Magnetic Nanoparticles via Magnetization Harmonics",
                "year": 2020,
                "venue": "Nanomaterials",
                "citation_count": 7,
                "reference_count": 20,
                "abstract": "The core size distribution is an important physical characteristic of magnetic nanoparticles (MNPs) because it seriously affects biomedical and biological applications. In this study, we proposed an improved method for estimating the distributions, which optimizes the excitation frequency based on AC susceptibility to avoid the effects of Brownian relaxation. Moreover, the first, third, and fifth magnetization harmonics under different excitation field strengths are used for estimating core size distributions to avoid measuring higher harmonics. The experiment results show that the improved AC harmonic method can accurately and quickly estimate the distribution of large core sizes compared with the method of static magnetization (M\u2013H) curves, which is a competitive advantage in MNP immunoassays.",
                "authors": [
                    {
                        "s2_author_id": "2116961203",
                        "name": "Yi Sun"
                    },
                    {
                        "s2_author_id": "49188262",
                        "name": "Na Ye"
                    },
                    {
                        "s2_author_id": "2155681103",
                        "name": "Dandan Wang"
                    },
                    {
                        "s2_author_id": "8640067",
                        "name": "Zhongzhou Du"
                    },
                    {
                        "s2_author_id": "49163176",
                        "name": "S. Bai"
                    },
                    {
                        "s2_author_id": "1863177",
                        "name": "Takashi Yoshida"
                    }
                ]
            },
            {
                "s2_paper_id": "4705bbb2acb68ebbc5d54f8712b1f6db66413a93",
                "title": "Single-Sided Magnetic Particle Imaging Using Planar Gradient Coil and Electric Scanning of Field Free Point",
                "year": 2016,
                "venue": "2016 International Conference of Asian Union of Magnetics Societies (ICAUMS)",
                "citation_count": 1,
                "reference_count": 0,
                "abstract": null,
                "authors": [
                    {
                        "s2_author_id": "2107577414",
                        "name": "K. Yamamoto"
                    },
                    {
                        "s2_author_id": "104532779",
                        "name": "K. Tanabe"
                    },
                    {
                        "s2_author_id": "49163176",
                        "name": "S. Bai"
                    },
                    {
                        "s2_author_id": "34459020",
                        "name": "T. Sasayama"
                    },
                    {
                        "s2_author_id": "2107780677",
                        "name": "T. Yoshida"
                    },
                    {
                        "s2_author_id": "2512701",
                        "name": "K. Enpuku"
                    }
                ]
            },
            {
                "s2_paper_id": "7e9be9862132a9a1e88d1330636165af5af6a75f",
                "title": "Development of Magnetic Nanoparticle Imaging Using Gradient Magnetic Field and Electric Scanning of Field Free Point",
                "year": 2015,
                "venue": "",
                "citation_count": 0,
                "reference_count": 0,
                "abstract": null,
                "authors": [
                    {
                        "s2_author_id": "49163176",
                        "name": "S. Bai"
                    }
                ]
            },
            {
                "s2_paper_id": "806e82da34d1014b8fcd48f763aab44122744d8d",
                "title": "Narrow-Band Magnetic Nanoparticle Imaging using Orthogonal Gradient Field",
                "year": 2015,
                "venue": "",
                "citation_count": 2,
                "reference_count": 0,
                "abstract": "Magnetic particle imaging (MPI) utilizing nonlinear magnetization of magnetic nanoparticles (MNPs) is a new technique for in vivo diagnosis in medical imaging. We have improved a narrow-band MPI system using an orthogonal gradient field and third-harmonic signal detection. An AC excitation field with Bac = 1 mT and f = 22.75 kHz was applied, and a third-harmonic signal from MNPs (f = 68.75 kHz) was detected. The sensitivity of detection was improved by choosing proper diameter of a pickup coil so that we could detect 100 \uf06dg of MNPs located as deep as z = 50 mm. A spatial resolution of ~4 mm was achieved by using a gradient field of 1 T/m. We demonstrated the detection of two MNP samples spaced 5 mm apart and located at z = 50 mm. The measured contour map of the voltage signal was converted to an MNP distribution using the singular value decomposition (SVD) method. We were able to accurately identify two MNP samples. We also demonstrate the imaging of the letter \"K\" composed of eleven MNP samples with 7-mm spacing, which demonstrated the validity of the present method.",
                "authors": [
                    {
                        "s2_author_id": "49163176",
                        "name": "S. Bai"
                    },
                    {
                        "s2_author_id": "4261285",
                        "name": "A. Hirokawa"
                    },
                    {
                        "s2_author_id": "104532779",
                        "name": "K. Tanabe"
                    },
                    {
                        "s2_author_id": "34459020",
                        "name": "T. Sasayama"
                    },
                    {
                        "s2_author_id": "1863177",
                        "name": "Takashi Yoshida"
                    },
                    {
                        "s2_author_id": "2512701",
                        "name": "K. Enpuku"
                    }
                ]
            },
            {
                "s2_paper_id": "b7fbc3401cc0d9757c985d6258fb46a4555a52f5",
                "title": "Effect of viscosity on harmonic signals from magnetic fluid",
                "year": 2015,
                "venue": "",
                "citation_count": 37,
                "reference_count": 14,
                "abstract": null,
                "authors": [
                    {
                        "s2_author_id": "1863177",
                        "name": "Takashi Yoshida"
                    },
                    {
                        "s2_author_id": "49163176",
                        "name": "S. Bai"
                    },
                    {
                        "s2_author_id": "4261285",
                        "name": "A. Hirokawa"
                    },
                    {
                        "s2_author_id": "104532779",
                        "name": "K. Tanabe"
                    },
                    {
                        "s2_author_id": "2512701",
                        "name": "K. Enpuku"
                    }
                ]
            },
            {
                "s2_paper_id": "d7826b27bad31bc007a472b025b8b5e929c659d2",
                "title": "Narrowband Magnetic Particle Imaging Utilizing Electric Scanning of Field Free Point",
                "year": 2015,
                "venue": "IEEE transactions on magnetics",
                "citation_count": 11,
                "reference_count": 16,
                "abstract": null,
                "authors": [
                    {
                        "s2_author_id": "49163176",
                        "name": "S. Bai"
                    },
                    {
                        "s2_author_id": "4261285",
                        "name": "A. Hirokawa"
                    },
                    {
                        "s2_author_id": "104532779",
                        "name": "K. Tanabe"
                    },
                    {
                        "s2_author_id": "34459020",
                        "name": "T. Sasayama"
                    },
                    {
                        "s2_author_id": "2107780677",
                        "name": "T. Yoshida"
                    },
                    {
                        "s2_author_id": "2512701",
                        "name": "K. Enpuku"
                    }
                ]
            },
            {
                "s2_paper_id": "eac8adb3a10122678a5b54bd969f8984388e0546",
                "title": "Narrowband magnetic nanoparticle imaging using cooled pickup coil and gradient field",
                "year": 2015,
                "venue": "",
                "citation_count": 5,
                "reference_count": 25,
                "abstract": null,
                "authors": [
                    {
                        "s2_author_id": "2512701",
                        "name": "K. Enpuku"
                    },
                    {
                        "s2_author_id": "2069070354",
                        "name": "T. Miyazaki"
                    },
                    {
                        "s2_author_id": "103345619",
                        "name": "M. Morishita"
                    },
                    {
                        "s2_author_id": "102862946",
                        "name": "Y. Tsujita"
                    },
                    {
                        "s2_author_id": "47751637",
                        "name": "M. Matsuo"
                    },
                    {
                        "s2_author_id": "49163176",
                        "name": "S. Bai"
                    },
                    {
                        "s2_author_id": "34459020",
                        "name": "T. Sasayama"
                    },
                    {
                        "s2_author_id": "1863177",
                        "name": "Takashi Yoshida"
                    }
                ]
            },
            {
                "s2_paper_id": "900652d55537778527cf01a26571621de1210173",
                "title": "Highly Sensitive Magnetic Nanoparticle Imaging Using Cooled-Cu/HTS-Superconductor Pickup Coils",
                "year": 2014,
                "venue": "IEEE transactions on applied superconductivity",
                "citation_count": 16,
                "reference_count": 18,
                "abstract": null,
                "authors": [
                    {
                        "s2_author_id": "48229504",
                        "name": "T. Morishige"
                    },
                    {
                        "s2_author_id": "30778211",
                        "name": "T. Mihaya"
                    },
                    {
                        "s2_author_id": "49163176",
                        "name": "S. Bai"
                    },
                    {
                        "s2_author_id": "2069070354",
                        "name": "T. Miyazaki"
                    },
                    {
                        "s2_author_id": "1863177",
                        "name": "Takashi Yoshida"
                    },
                    {
                        "s2_author_id": "47751637",
                        "name": "M. Matsuo"
                    },
                    {
                        "s2_author_id": "2512701",
                        "name": "K. Enpuku"
                    }
                ]
            },
            {
                "s2_paper_id": "df4214e9121148fd443b5e8b61f21079041cba7b",
                "title": "The effect of Neel relaxation on the properties of the third harmonic signal of magnetic nanoparticles for use in narrow-band magnetic nanoparticle imaging",
                "year": 2014,
                "venue": "",
                "citation_count": 15,
                "reference_count": 20,
                "abstract": null,
                "authors": [
                    {
                        "s2_author_id": "2512701",
                        "name": "K. Enpuku"
                    },
                    {
                        "s2_author_id": "49163176",
                        "name": "S. Bai"
                    },
                    {
                        "s2_author_id": "4261285",
                        "name": "A. Hirokawa"
                    },
                    {
                        "s2_author_id": "104532779",
                        "name": "K. Tanabe"
                    },
                    {
                        "s2_author_id": "34459020",
                        "name": "T. Sasayama"
                    },
                    {
                        "s2_author_id": "1863177",
                        "name": "Takashi Yoshida"
                    }
                ]
            },
            {
                "s2_paper_id": "e0f5474fca1b49df3c01a1c0428c106c3b554264",
                "title": "Magnetic Particle Imaging System Utilizing Orthogonal Gradient Field and Harmonic Signal Detection",
                "year": 2014,
                "venue": "",
                "citation_count": 1,
                "reference_count": 0,
                "abstract": null,
                "authors": [
                    {
                        "s2_author_id": "49163176",
                        "name": "S. Bai"
                    },
                    {
                        "s2_author_id": "103576101",
                        "name": "D. Kitahara"
                    },
                    {
                        "s2_author_id": "4261285",
                        "name": "A. Hirokawa"
                    },
                    {
                        "s2_author_id": "1863177",
                        "name": "Takashi Yoshida"
                    },
                    {
                        "s2_author_id": "2512701",
                        "name": "K. Enpuku"
                    }
                ]
            },
            {
                "s2_paper_id": "edba2b935bd21e8ba9dcb4f98de56476a94c4ea4",
                "title": "Magnetic Particle Imaging Utilizing Orthogonal Gradient Field and Third-Harmonic Signal Detection",
                "year": 2014,
                "venue": "IEEE transactions on magnetics",
                "citation_count": 5,
                "reference_count": 13,
                "abstract": null,
                "authors": [
                    {
                        "s2_author_id": "49163176",
                        "name": "S. Bai"
                    },
                    {
                        "s2_author_id": "4261285",
                        "name": "A. Hirokawa"
                    },
                    {
                        "s2_author_id": "104532779",
                        "name": "K. Tanabe"
                    },
                    {
                        "s2_author_id": "1863177",
                        "name": "Takashi Yoshida"
                    },
                    {
                        "s2_author_id": "2512701",
                        "name": "K. Enpuku"
                    }
                ]
            },
            {
                "s2_paper_id": "f388884e7ba58497e75a3fa393a35e09d6d00365",
                "title": "Design of Optical Measuring Equipment for Sea Surface Microstructure",
                "year": 2001,
                "venue": "",
                "citation_count": 0,
                "reference_count": 0,
                "abstract": null,
                "authors": [
                    {
                        "s2_author_id": "49163176",
                        "name": "S. Bai"
                    }
                ]
            }
        ],
        "co_authors": [
            {
                "s2_author_id": "48064203",
                "name": "Lijian Yang"
            },
            {
                "s2_author_id": "2153791522",
                "name": "Fuyin Zheng"
            },
            {
                "s2_author_id": "2119408411",
                "name": "Ping Huang"
            },
            {
                "s2_author_id": "15531317",
                "name": "Yuming Su"
            },
            {
                "s2_author_id": "119607717",
                "name": "Yuxiang Yang"
            },
            {
                "s2_author_id": "2152782186",
                "name": "Hai Lin"
            },
            {
                "s2_author_id": "2109036715",
                "name": "Jianmin Li"
            },
            {
                "s2_author_id": "150106477",
                "name": "Fu Zhang"
            },
            {
                "s2_author_id": "8640067",
                "name": "Zhongzhou Du"
            },
            {
                "s2_author_id": "144010725",
                "name": "B. Hu"
            },
            {
                "s2_author_id": "49188262",
                "name": "Na Ye"
            },
            {
                "s2_author_id": "2116961203",
                "name": "Yi Sun"
            },
            {
                "s2_author_id": "2244605509",
                "name": "Haochen Zhang"
            },
            {
                "s2_author_id": "2121069982",
                "name": "J. Ri"
            },
            {
                "s2_author_id": "2048081196",
                "name": "N. Pang"
            },
            {
                "s2_author_id": "2146301380",
                "name": "Jialin Xu"
            },
            {
                "s2_author_id": "2126044645",
                "name": "Lisheng Xu"
            },
            {
                "s2_author_id": "104224113",
                "name": "Songchol Ri"
            },
            {
                "s2_author_id": "2152877654",
                "name": "Yudong Yao"
            },
            {
                "s2_author_id": "31726364",
                "name": "S. Greenwald"
            },
            {
                "s2_author_id": "3246432",
                "name": "YanYing Cui"
            },
            {
                "s2_author_id": "1863177",
                "name": "Takashi Yoshida"
            },
            {
                "s2_author_id": "152392321",
                "name": "Ping Huang"
            },
            {
                "s2_author_id": "9355542",
                "name": "Song-wei Gao"
            },
            {
                "s2_author_id": "34459020",
                "name": "T. Sasayama"
            },
            {
                "s2_author_id": "2044447837",
                "name": "Zhouzhong Du"
            },
            {
                "s2_author_id": "2155681103",
                "name": "Dandan Wang"
            },
            {
                "s2_author_id": "103538013",
                "name": "Oji Higashi"
            },
            {
                "s2_author_id": "2038374944",
                "name": "Y. Noguchi"
            },
            {
                "s2_author_id": "2512701",
                "name": "K. Enpuku"
            },
            {
                "s2_author_id": "2107577414",
                "name": "K. Yamamoto"
            },
            {
                "s2_author_id": "104532779",
                "name": "K. Tanabe"
            },
            {
                "s2_author_id": "2107780677",
                "name": "T. Yoshida"
            },
            {
                "s2_author_id": "4261285",
                "name": "A. Hirokawa"
            },
            {
                "s2_author_id": "2069070354",
                "name": "T. Miyazaki"
            },
            {
                "s2_author_id": "103345619",
                "name": "M. Morishita"
            },
            {
                "s2_author_id": "102862946",
                "name": "Y. Tsujita"
            },
            {
                "s2_author_id": "47751637",
                "name": "M. Matsuo"
            },
            {
                "s2_author_id": "48229504",
                "name": "T. Morishige"
            },
            {
                "s2_author_id": "30778211",
                "name": "T. Mihaya"
            },
            {
                "s2_author_id": "103576101",
                "name": "D. Kitahara"
            }
        ],
        "total_co_authors": 41,
        "papers_retrieved": 21
    }
}